Metadata-Version: 2.1
Name: django-qd
Version: 0.0
Summary: Django Query Debbuger
Home-page: UNKNOWN
Author-email: quantumastelata@gmail.com
License: UNKNOWN
Platform: UNKNOWN
